setup.cfg
setup.py
flask_clapi/__init__.py
flask_clapi.egg-info/PKG-INFO
flask_clapi.egg-info/SOURCES.txt
flask_clapi.egg-info/dependency_links.txt
flask_clapi.egg-info/requires.txt
flask_clapi.egg-info/top_level.txt