Metadata-Version: 1.1
Name: flask-clapi
Version: 0.2.0
Summary: CLAPI wrapper
Home-page: https://github.com/rbw0/flask_clapi
Author: Robert Wikman
Author-email: rbw@vault13.org
License: GPLv2
Download-URL: https://github.com/rbw0/flask_clapi/tarball/0.2.0
Keywords: flask,clapi,wrapper,Centreon
Platform: UNKNOWN
